pyhrv/README.md
pyhrv/__init__.py
pyhrv/__version__.py
pyhrv/frequency_domain.py
pyhrv/hrv.py
pyhrv/nonlinear.py
pyhrv/time_domain.py
pyhrv/tools.py
pyhrv/utils.py
pyhrv/files/SampleECG.txt
pyhrv/files/SampleExport.json
pyhrv/files/SampleNNISeriesLong.npy
pyhrv/files/SampleNNISeriesShort.npy
pyhrv/files/SampleReport.csv
pyhrv/files/SampleReport.pdf
pyhrv/files/SampleReport.txt
pyhrv/files/hr_heatplot.json
pyhrv/files/hrv_keys.json
pyhrv/files/references.txt
pyhrv/files/quickstart/ar_custom.png
pyhrv/files/quickstart/ar_default.png
pyhrv/files/quickstart/dfa.png
pyhrv/files/quickstart/ecg15.png
pyhrv/files/quickstart/function_levels.png
pyhrv/files/quickstart/lomb_custom.png
pyhrv/files/quickstart/lomb_default.png
pyhrv/files/quickstart/poincare.png
pyhrv/files/quickstart/pyhrv.png
pyhrv/files/quickstart/tachogram15.png
pyhrv/files/quickstart/welch_custom.png
pyhrv/files/quickstart/welch_default.png
pyhrv/report/__init__.py
pyhrv-0.4.1.dist-info/LICENSE.txt
pyhrv-0.4.1.dist-info/METADATA
pyhrv-0.4.1.dist-info/WHEEL
pyhrv-0.4.1.dist-info/top_level.txt
pyhrv-0.4.1.dist-info/RECORD
