Metadata-Version: 2.1
Name: pyhrv
Version: 0.4.1
Summary: Python toolbox for Heart Rate Variability.
Home-page: https://github.com/PGomes92/pyhrv
Author: Pedro Gomes
Author-email: pgomes92@gmail.com
License: UNKNOWN
Keywords: Heart Rate Variability,HRV
Platform: UNKNOWN
Classifier: Intended Audience :: Developers
Classifier: Intended Audience :: Education
Classifier: Intended Audience :: Science/Research
Classifier: Natural Language :: English
Classifier: License :: OSI Approved :: BSD License
Classifier: Programming Language :: Python
Classifier: Programming Language :: Python :: 2.7
Classifier: Programming Language :: Python :: 3.4
Classifier: Programming Language :: Python :: 3.5
Classifier: Programming Language :: Python :: 3.6
Classifier: Programming Language :: Python :: 3.7
Classifier: Operating System :: OS Independent
Requires-Python: >=2.7
License-File: LICENSE.txt
